arena_integrations/__init__.py
arena_integrations/databricks.py
arena_integrations/tests/test_databricks.py
arena_integrations-0.0.8.dist-info/METADATA
arena_integrations-0.0.8.dist-info/WHEEL
arena_integrations-0.0.8.dist-info/RECORD
